demux4x1.v
module demux1x4
(
    input d,
    input s1, s0,
    output y0, y1, y2, y3
);

assign y0 = d & ~s1 & ~s0;
assign y1 = d & ~s1 &  s0;
assign y2 = d &  s1 & ~s0;
assign y3 = d &  s1 &  s0;

endmodule

demux1x16.v

module demux1x16(
    input d,
    input s3, s2, s1, s0,
    output [15:0] y
);

wire w0, w1, w2, w3;

//stage1

demux1x4 d0(d, s3, s2, w0, w1, w2, w3);

//stage2

demux1x4 d1(w0, s1, s0, y[0],  y[1],  y[2],  y[3]);

demux1x4 d2(w1, s1, s0, y[4],  y[5],  y[6],  y[7]);

demux1x4 d3(w2, s1, s0, y[8],  y[9],  y[10], y[11]);

demux1x4 d4(w3, s1, s0, y[12], y[13], y[14], y[15]);

endmodule

demux1x16_tb.v
module test;

reg d;
reg [3:0] s;

wire [15:0] y;

integer i;

demux1x16 uut
(
    d, s[3], s[2], s[1], s[0], y
);

initial begin

    $dumpfile("wave.vcd");
    $dumpvars(0, test);

    d = 1;

    for(i = 0; i < 16; i = i + 1)
    begin
        s = i;
        #10;
    end

    $finish;

end
endmodule

wave.vcd
$date
	Mon May 11 09:10:23 2026
$end
$version
	Icarus Verilog
$end
$timescale
	1s
$end
$scope module test $end
$var wire 16 ! y [15:0] $end
$var reg 1 " d $end
$var reg 4 # s [3:0] $end
$var integer 32 $ i [31:0] $end
$scope module uut $end
$var wire 1 " d $end
$var wire 1 % s0 $end
$var wire 1 & s1 $end
$var wire 1 ' s2 $end
$var wire 1 ( s3 $end
$var wire 16 ) y [15:0] $end
$var wire 1 * w3 $end
$var wire 1 + w2 $end
$var wire 1 , w1 $end
$var wire 1 - w0 $end
$scope module d0 $end
$var wire 1 " d $end
$var wire 1 ' s0 $end
$var wire 1 ( s1 $end
$var wire 1 - y0 $end
$var wire 1 , y1 $end
$var wire 1 + y2 $end
$var wire 1 * y3 $end
$upscope $end
$scope module d1 $end
$var wire 1 - d $end
$var wire 1 % s0 $end
$var wire 1 & s1 $end
$var wire 1 . y0 $end
$var wire 1 / y1 $end
$var wire 1 0 y2 $end
$var wire 1 1 y3 $end
$upscope $end
$scope module d2 $end
$var wire 1 , d $end
$var wire 1 % s0 $end
$var wire 1 & s1 $end
$var wire 1 2 y0 $end
$var wire 1 3 y1 $end
$var wire 1 4 y2 $end
$var wire 1 5 y3 $end
$upscope $end
$scope module d3 $end
$var wire 1 + d $end
$var wire 1 % s0 $end
$var wire 1 & s1 $end
$var wire 1 6 y0 $end
$var wire 1 7 y1 $end
$var wire 1 8 y2 $end
$var wire 1 9 y3 $end
$upscope $end
$scope module d4 $end
$var wire 1 * d $end
$var wire 1 % s0 $end
$var wire 1 & s1 $end
$var wire 1 : y0 $end
$var wire 1 ; y1 $end
$var wire 1 < y2 $end
$var wire 1 = y3 $end
$upscope $end
$upscope $end
$upscope $end
$enddefinitions $end
$comment Show the parameter values. $end
$dumpall
$end
#0
$dumpvars
0=
0<
0;
0:
09
08
07
06
05
04
03
02
01
00
0/
1.
1-
0,
0+
0*
b1 )
0(
0'
0&
0%
b0 $
b0 #
1"
b1 !
$end
#10
0.
b10 !
b10 )
1/
1%
b1 #
b1 $
#20
0.
10
b100 !
b100 )
0/
1&
0%
b10 #
b10 $
#30
00
b1000 !
b1000 )
11
1%
b11 #
b11 $
#40
0.
12
0-
1,
b10000 !
b10000 )
01
1'
0&
0%
b100 #
b100 $
#50
02
b100000 !
b100000 )
13
1%
b101 #
b101 $
#60
02
14
b1000000 !
b1000000 )
03
1&
0%
b110 #
b110 $
#70
04
b10000000 !
b10000000 )
15
1%
b111 #
b111 $
#80
0.
16
0-
1+
0,
b100000000 !
b100000000 )
05
1(
0'
0&
0%
b1000 #
b1000 $
#90
06
b1000000000 !
b1000000000 )
17
1%
b1001 #
b1001 $
#100
06
18
b10000000000 !
b10000000000 )
07
1&
0%
b1010 #
b1010 $
#110
08
b100000000000 !
b100000000000 )
19
1%
b1011 #
b1011 $
#120
06
1:
0+
1*
b1000000000000 !
b1000000000000 )
09
1'
0&
0%
b1100 #
b1100 $
#130
0:
b10000000000000 !
b10000000000000 )
1;
1%
b1101 #
b1101 $
#140
0:
1<
b100000000000000 !
b100000000000000 )
0;
1&
0%
b1110 #
b1110 $
#150
0<
b1000000000000000 !
b1000000000000000 )
1=
1%
b1111 #
b1111 $
#160
b10000 $
